{
    "format_version": "1.8.0",
    "minecraft:client_entity": {
        "description": {
            "identifier": "sunrise:hunter",
            "min_engine_version": "1.8.0",
            "materials": {
                "default": "stray"
            },
            "textures": {
                "skin1": "textures/entity/hunter/hunter1",
                "skin2": "textures/entity/hunter/hunter2",
                "skin3": "textures/entity/hunter/hunter3",
                "skin4": "textures/entity/hunter/hunter4",
                "skin5": "textures/entity/hunter/hunter5_slim",
                "skin6": "textures/entity/hunter/hunter6_slim",
                "skin7": "textures/entity/hunter/hunter7_slim",
                "skin8": "textures/entity/hunter/hunter8_slim",
                "skin9": "textures/entity/hunter/hunter9",
                "skin10": "textures/entity/hunter/hunter10",
                "skin11": "textures/entity/hunter/hunter11",
                "skin12": "textures/entity/hunter/hunter12_slim",
                "skin13": "textures/entity/hunter/hunter13",
                "skin14": "textures/entity/hunter/hunter14"
            },
            "geometry": {
                "default": "geometry.mas",
                "slim": "geometry.slim"
            },
            "spawn_egg": {
                "texture": "spawnegg_hunter",
                "texture_index": 0
            },
            "scripts": {
                "pre_animation": [
                    "variable.tcos0 = (Math.cos(query.modified_distance_moved * 38.17) * query.modified_move_speed / variable.gliding_speed_value) * 57.3;"
                ]
            },
            "animations": {
                "look_at_target_default": "animation.humanoid.look_at_target.default",
                "look_at_target_gliding": "animation.humanoid.look_at_target.gliding",
                "look_at_target_swimming": "animation.humanoid.look_at_target.swimming",
                "move": "animation.humanoid.move",
                "riding.arms": "animation.humanoid.riding.arms",
                "riding.legs": "animation.humanoid.riding.legs",
                "holding": "animation.humanoid.holding",
                "brandish_spear": "animation.humanoid.brandish_spear",
                "charging": "animation.humanoid.charging",
                "attack.rotations": "animation.humanoid.attack.rotations",
                "sneaking": "animation.humanoid.sneaking",
                "bob": "animation.humanoid.bob",
                "damage_nearby_mobs": "animation.humanoid.damage_nearby_mobs",
                "swimming": "animation.zombie.swimming",
                "use_item_progress": "animation.humanoid.use_item_progress"
            },
            "animation_controllers": [
                {
                    "look_at_target": "controller.animation.humanoid.look_at_target"
                },
                {
                    "move": "controller.animation.humanoid.move"
                },
                {
                    "riding": "controller.animation.humanoid.riding"
                },
                {
                    "holding": "controller.animation.humanoid.holding"
                },
                {
                    "brandish_spear": "controller.animation.humanoid.brandish_spear"
                },
                {
                    "charging": "controller.animation.humanoid.charging"
                },
                {
                    "sneaking": "controller.animation.humanoid.sneaking"
                },
                {
                    "bob": "controller.animation.humanoid.bob"
                },
                {
                    "swimming": "controller.animation.zombie.swimming"
                },
                {
                    "use_item_progress": "controller.animation.humanoid.use_item_progress"
                }
            ],
            "render_controllers": [
                "controller.render.vampiro_simples"
            ],
            "enable_attachables": true
        }
    }
}
